rustgi-0.1.22.dist-info/METADATA
rustgi-0.1.22.dist-info/WHEEL
rustgi-0.1.22.dist-info/licenses/LICENSE
rustgi/__init__.py
rustgi/rustgi.pypy38-pp73-ppc_64-linux-gnu.so
rustgi-0.1.22.dist-info/RECORD
