Metadata-Version: 2.3
Name: rustgi
Version: 0.1.22
Classifier: Programming Language :: Rust
Classifier: Programming Language :: Python :: Implementation :: CPython
Classifier: Programming Language :: Python :: Implementation :: PyPy
Classifier: Operating System :: MacOS
Classifier: Operating System :: POSIX :: Linux
Classifier: Programming Language :: Python :: 3.10
Classifier: Programming Language :: Python :: 3.11
Classifier: Programming Language :: Python :: Implementation :: CPython
Classifier: Programming Language :: Python :: Implementation :: PyPy
Classifier: Programming Language :: Python
Classifier: Programming Language :: Rust
Classifier: Topic :: Internet :: WWW/HTTP
License-File: LICENSE
Author-email: Lâm Hoàng Phúc <eddiebrock2001@gmail.com>
Requires-Python: >=3.7
